streamsketchlib/__init__.py
streamsketchlib/bloom_filter.py
streamsketchlib/count_min.py
streamsketchlib/distinct_count.py
streamsketchlib/distinct_count_algorithms.py
streamsketchlib/f2_estimate.py
streamsketchlib/heavy_hitters.py
streamsketchlib/heavy_hitters_algorithms.py
streamsketchlib/heavy_hitters_cm.py
streamsketchlib/minhash.py
streamsketchlib/rsv_sampling.py
sketchlib-0.0.2.dist-info/LICENSE
sketchlib-0.0.2.dist-info/METADATA
sketchlib-0.0.2.dist-info/WHEEL
sketchlib-0.0.2.dist-info/top_level.txt
sketchlib-0.0.2.dist-info/RECORD
