Metadata-Version: 2.1
Name: sketchlib
Version: 0.0.2
Summary: Library of streaming algorithms for processing massive data.
Author-email: "Dr. Hoa Vu and Daniel Barnas" <danielbarn90@gmail.com>
License: The MIT License (MIT)
Project-URL: Homepage, https://datasketchlib.github.io/
Keywords: streaming,algorithms,big,massive,data
Classifier: License :: OSI Approved :: MIT License
Classifier: Programming Language :: Python
Classifier: Programming Language :: Python :: 3
Requires-Python: >=3.9
License-File: LICENSE
Requires-Dist: mmh3 (>=3.1.0)
Requires-Dist: tomli ; python_version < "3.11"
Provides-Extra: dev
Requires-Dist: black ; extra == 'dev'
Requires-Dist: bumpver ; extra == 'dev'
Requires-Dist: isort ; extra == 'dev'
Requires-Dist: pip-tools ; extra == 'dev'
Requires-Dist: pytest ; extra == 'dev'
